ipc_frontier/__init__.py
ipc_frontier/__main__.py
ipc_frontier/cli.py
ipc_frontier/py.typed
ipc_frontier_py-0.1.11.dist-info/METADATA
ipc_frontier_py-0.1.11.dist-info/WHEEL
ipc_frontier_py-0.1.11.dist-info/entry_points.txt
ipc_frontier_py-0.1.11.dist-info/licenses/LICENSE
ipc_frontier_py-0.1.11.dist-info/RECORD
