Metadata-Version: 2.4
Name: ipc-frontier-py
Version: 0.1.11
Summary: Benchmarks comparing Python concurrency models--threads, Queue-based multiprocessing, and SharedMemory-based multiprocessing--for moving and processing NumPy arrays.
License-File: LICENSE
Keywords: concurrency,threading,multiprocessing,ipc,shared-memory,serialization,numpy,benchmark,performance
Author: Ryan Wallace
Author-email: ryancswallace@gmail.com
Requires-Python: ~=3.13.0
Classifier: Intended Audience :: Developers
Classifier: Intended Audience :: Science/Research
Classifier: Environment :: Console
Classifier: Natural Language :: English
Classifier: Operating System :: OS Independent
Classifier: Programming Language :: Python :: 3
Classifier: Programming Language :: Python :: 3 :: Only
Classifier: Programming Language :: Python :: 3.13
Classifier: Typing :: Typed
Classifier: Topic :: System :: Benchmark
Classifier: Topic :: System :: Distributed Computing
Classifier: Topic :: Scientific/Engineering :: Artificial Intelligence
Classifier: License :: OSI Approved :: MIT License
Requires-Dist: numpy (>=2.3.3,<3.0.0)
Project-URL: Bug Tracker, https://github.com/ryancswallace/ipc-frontier-py/issues
Project-URL: Documentation, https://github.com/ryancswallace/ipc-frontier-py
Project-URL: Homepage, https://github.com/ryancswallace/ipc-frontier-py
Project-URL: Repository, https://github.com/ryancswallace/ipc-frontier-py
